hamt_sharding/__init__.py
hamt_sharding/buckets.py
hamt_sharding/consumable_buffer.py
hamt_sharding/consumable_hash.py
hamt_sharding/py.typed
hamt_sharding-0.1.3.dist-info/METADATA
hamt_sharding-0.1.3.dist-info/WHEEL
hamt_sharding-0.1.3.dist-info/top_level.txt
hamt_sharding-0.1.3.dist-info/RECORD
