Metadata-Version: 2.1
Name: hamt-sharding
Version: 0.1.3
Summary: Python implementation of hamt-sharding.
Home-page: https://github.com/kralverde/py-hamt-sharding/
Author: kralverde
Project-URL: Bug Tracker, https://github.com/kralverde/py-hamt-sharding/issues
Classifier: Development Status :: 3 - Alpha
Classifier: Programming Language :: Python :: 3.11
Classifier: Programming Language :: Python :: 3.10
Classifier: Programming Language :: Python :: 3.9
Classifier: Programming Language :: Python :: 3.8
Classifier: Programming Language :: Python :: 3.7
Classifier: Operating System :: OS Independent
Classifier: Natural Language :: English
Classifier: Typing :: Typed
Requires-Python: >=3.7
Requires-Dist: attrs >=20.1.0
Requires-Dist: bitmap-sparse-array >=0.1.3
